dahi/__init__.py
dahi/bot.py
dahi/bots.py
dahi/context.py
dahi/contexts.py
dahi/document.py
dahi/documents.py
dahi/example2.py
dahi/knowledgebase.py
dahi/nlu.py
dahi/statement.py
dahi/storages.py
dahi/matchers/__init__.py
dahi/matchers/__init__.pyc
dahi/matchers/abstracts.py
dahi/matchers/abstracts.pyc
dahi/matchers/tfidfMatcher.py
dahi/matchers/tfidfMatcher.pyc
dahi-0.1.2.dist-info/DESCRIPTION.rst
dahi-0.1.2.dist-info/METADATA
dahi-0.1.2.dist-info/RECORD
dahi-0.1.2.dist-info/WHEEL
dahi-0.1.2.dist-info/metadata.json
dahi-0.1.2.dist-info/top_level.txt
