Metadata-Version: 2.0
Name: dahi
Version: 0.1.2
Summary: question answer bot
Home-page: https://github.com/muatik/dahi
Author: Mustafa Atik
Author-email: muatik@gmail.com
License: The MIT License (MIT)
Requires-Dist: Sphinx
Requires-Dist: flask
Requires-Dist: pymongo
Requires-Dist: sphinx-autobuild
Requires-Dist: sphinx-rtd-theme
